{"data":[{"time":1544205600000,"participants":125730,"ranking50p":"62865","ranking25p":"62865","ranking10p":"31433","ranking5p":"6287","ranking1p":"1257","key1participants":91864,"key2participants":69406,"key3participants":51405,"key4participants":47585,"key5participants":44493,"key6participants":11832,"key7participants":11126,"key8participants":10517,"key9participants":6305},{"time":1544292000000,"participants":125730,"ranking50p":"62865","ranking25p":"62865","ranking10p":"31433","ranking5p":"6287","ranking1p":"1257","key1participants":91864,"key2participants":69406,"key3participants":51405,"key4participants":47585,"key5participants":44493,"key6participants":11832,"key7participants":11126,"key8participants":10517,"key9participants":6305},{"time":1544378400000,"participants":125730,"ranking50p":"62865","ranking25p":"62865","ranking10p":"31433","ranking5p":"6287","ranking1p":"1257","key1participants":91864,"key2participants":69406,"key3participants":51405,"key4participants":47585,"key5participants":44493,"key6participants":11832,"key7participants":11126,"key8participants":10517,"key9participants":6305},{"time":1544464800000,"participants":125730,"ranking50p":"62865","ranking25p":"62865","ranking10p":"31433","ranking5p":"6287","ranking1p":"1257","key1participants":91864,"key2participants":69406,"key3participants":51405,"key4participants":47585,"key5participants":44493,"key6participants":11832,"key7participants":11126,"key8participants":10517,"key9participants":6305},{"time":1544551200000,"participants":125730,"ranking50p":"62865","ranking25p":"62865","ranking10p":"31433","ranking5p":"6287","ranking1p":"1257","key1participants":91864,"key2participants":69406,"key3participants":51405,"key4participants":47585,"key5participants":44493,"key6participants":11832,"key7participants":11126,"key8participants":10517,"key9participants":6305},{"time":1544637600000,"participants":125730,"ranking50p":"62865","ranking25p":"62865","ranking10p":"31433","ranking5p":"6287","ranking1p":"1257","key1participants":91864,"key2participants":69406,"key3participants":51405,"key4participants":47585,"key5participants":44493,"key6participants":11832,"key7participants":11126,"key8participants":10517,"key9participants":6305},{"time":1544724000000,"participants":125730,"ranking50p":"62865","ranking25p":"62865","ranking10p":"31433","ranking5p":"6287","ranking1p":"1257","key1participants":91864,"key2participants":69406,"key3participants":51405,"key4participants":47585,"key5participants":44493,"key6participants":11832,"key7participants":11126,"key8participants":10517,"key9participants":6305},{"time":1544810400000,"participants":125730,"ranking50p":"62865","ranking25p":"62865","ranking10p":"31433","ranking5p":"6287","ranking1p":"1257","key1participants":91864,"key2participants":69406,"key3participants":51405,"key4participants":47585,"key5participants":44493,"key6participants":11832,"key7participants":11126,"key8participants":10517,"key9participants":6305},{"time":1544896800000,"participants":125730,"ranking50p":"62865","ranking25p":"62865","ranking10p":"31433","ranking5p":"6287","ranking1p":"1257","key1participants":91864,"key2participants":69406,"key3participants":51405,"key4participants":47585,"key5participants":44493,"key6participants":11832,"key7participants":11126,"key8participants":10517,"key9participants":6305},{"time":1544983200000,"participants":125730,"ranking50p":"62865","ranking25p":"62865","ranking10p":"31433","ranking5p":"6287","ranking1p":"1257","key1participants":91864,"key2participants":69406,"key3participants":51405,"key4participants":47585,"key5participants":44493,"key6participants":11832,"key7participants":11126,"key8participants":10517,"key9participants":6305},{"time":1545069600000,"participants":125730,"ranking50p":"62865","ranking25p":"62865","ranking10p":"31433","ranking5p":"6287","ranking1p":"1257","key1participants":91864,"key2participants":69406,"key3participants":51405,"key4participants":47585,"key5participants":44493,"key6participants":11832,"key7participants":11126,"key8participants":10517,"key9participants":6305},{"time":1545156000000,"participants":125730,"ranking50p":"62865","ranking25p":"62865","ranking10p":"31433","ranking5p":"6287","ranking1p":"1257","key1participants":91864,"key2participants":69406,"key3participants":51405,"key4participants":47585,"key5participants":44493,"key6participants":11832,"key7participants":11126,"key8participants":10517,"key9participants":6305},{"time":1545242400000,"participants":125730,"ranking50p":"62865","ranking25p":"62865","ranking10p":"31433","ranking5p":"6287","ranking1p":"1257","key1participants":91864,"key2participants":69406,"key3participants":51405,"key4participants":47585,"key5participants":44493,"key6participants":11832,"key7participants":11126,"key8participants":10517,"key9participants":6305},{"time":1545328800000,"participants":125730,"ranking50p":"62865","ranking25p":"62865","ranking10p":"31433","ranking5p":"6287","ranking1p":"1257","key1participants":91864,"key2participants":69406,"key3participants":51405,"key4participants":47585,"key5participants":44493,"key6participants":11832,"key7participants":11126,"key8participants":10517,"key9participants":6305},{"time":1545415200000,"participants":125730,"ranking50p":"62865","ranking25p":"62865","ranking10p":"31433","ranking5p":"6287","ranking1p":"1257","key1participants":91864,"key2participants":69406,"key3participants":51405,"key4participants":47585,"key5participants":44493,"key6participants":11832,"key7participants":11126,"key8participants":10517,"key9participants":6305},{"time":1545501600000,"participants":125730,"ranking50p":"62865","ranking25p":"62865","ranking10p":"31433","ranking5p":"6287","ranking1p":"1257","key1participants":91864,"key2participants":69406,"key3participants":51405,"key4participants":47585,"key5participants":44493,"key6participants":11832,"key7participants":11126,"key8participants":10517,"key9participants":6305},{"time":1545588000000,"participants":125730,"ranking50p":"62865","ranking25p":"62865","ranking10p":"31433","ranking5p":"6287","ranking1p":"1257","key1participants":91864,"key2participants":69406,"key3participants":51405,"key4participants":47585,"key5participants":44493,"key6participants":11832,"key7participants":11126,"key8participants":10517,"key9participants":6305},{"time":1545674400000,"participants":125730,"ranking50p":"62865","ranking25p":"62865","ranking10p":"31433","ranking5p":"6287","ranking1p":"1257","key1participants":91864,"key2participants":69406,"key3participants":51405,"key4participants":47585,"key5participants":44493,"key6participants":11832,"key7participants":11126,"key8participants":10517,"key9participants":6305},{"time":1545760800000,"participants":125730,"ranking50p":"62865","ranking25p":"62865","ranking10p":"31433","ranking5p":"6287","ranking1p":"1257","key1participants":91864,"key2participants":69406,"key3participants":51405,"key4participants":47585,"key5participants":44493,"key6participants":11832,"key7participants":11126,"key8participants":10517,"key9participants":6305},{"time":1545847200000,"participants":125730,"ranking50p":"62865","ranking25p":"62865","ranking10p":"31433","ranking5p":"6287","ranking1p":"1257","key1participants":91864,"key2participants":69406,"key3participants":51405,"key4participants":47585,"key5participants":44493,"key6participants":11832,"key7participants":11126,"key8participants":10517,"key9participants":6305},{"time":1545933600000,"participants":125730,"ranking50p":"62865","ranking25p":"62865","ranking10p":"31433","ranking5p":"6287","ranking1p":"1257","key1participants":91864,"key2participants":69406,"key3participants":51405,"key4participants":47585,"key5participants":44493,"key6participants":11832,"key7participants":11126,"key8participants":10517,"key9participants":6305},{"time":1546020000000,"participants":125730,"ranking50p":"62865","ranking25p":"62865","ranking10p":"31433","ranking5p":"6287","ranking1p":"1257","key1participants":91864,"key2participants":69406,"key3participants":51405,"key4participants":47585,"key5participants":44493,"key6participants":11832,"key7participants":11126,"key8participants":10517,"key9participants":6305},{"time":1546106400000,"participants":125730,"ranking50p":"62865","ranking25p":"62865","ranking10p":"31433","ranking5p":"6287","ranking1p":"1257","key1participants":91864,"key2participants":69406,"key3participants":51405,"key4participants":47585,"key5participants":44493,"key6participants":11832,"key7participants":11126,"key8participants":10517,"key9participants":6305},{"time":1546192800000,"participants":125730,"ranking50p":"62865","ranking25p":"62865","ranking10p":"31433","ranking5p":"6287","ranking1p":"1257","key1participants":91864,"key2participants":69406,"key3participants":51405,"key4participants":47585,"key5participants":44493,"key6participants":11832,"key7participants":11126,"key8participants":10517,"key9participants":6305},{"time":1546279200000,"participants":125730,"ranking50p":"62865","ranking25p":"62865","ranking10p":"31433","ranking5p":"6287","ranking1p":"1257","key1participants":91864,"key2participants":69406,"key3participants":51405,"key4participants":47585,"key5participants":44493,"key6participants":11832,"key7participants":11126,"key8participants":10517,"key9participants":6305},{"time":1546365600000,"participants":125730,"ranking50p":"62865","ranking25p":"62865","ranking10p":"31433","ranking5p":"6287","ranking1p":"1257","key1participants":91864,"key2participants":69406,"key3participants":51405,"key4participants":47585,"key5participants":44493,"key6participants":11832,"key7participants":11126,"key8participants":10517,"key9participants":6305},{"time":1546452000000,"participants":125730,"ranking50p":"62865","ranking25p":"62865","ranking10p":"31433","ranking5p":"6287","ranking1p":"1257","key1participants":91864,"key2participants":69406,"key3participants":51405,"key4participants":47585,"key5participants":44493,"key6participants":11832,"key7participants":11126,"key8participants":10517,"key9participants":6305},{"time":1546538400000,"participants":125730,"ranking50p":"62865","ranking25p":"62865","ranking10p":"31433","ranking5p":"6287","ranking1p":"1257","key1participants":91864,"key2participants":69406,"key3participants":51405,"key4participants":47585,"key5participants":44493,"key6participants":11832,"key7participants":11126,"key8participants":10517,"key9participants":6305},{"time":1546624800000,"participants":125730,"ranking50p":"62865","ranking25p":"62865","ranking10p":"31433","ranking5p":"6287","ranking1p":"1257","key1participants":91864,"key2participants":69406,"key3participants":51405,"key4participants":47585,"key5participants":44493,"key6participants":11832,"key7participants":11126,"key8participants":10517,"key9participants":6305},{"time":1546711200000,"participants":125730,"ranking50p":"62865","ranking25p":"62865","ranking10p":"31433","ranking5p":"6287","ranking1p":"1257","key1participants":91864,"key2participants":69406,"key3participants":51405,"key4participants":47585,"key5participants":44493,"key6participants":11832,"key7participants":11126,"key8participants":10517,"key9participants":6305},{"time":1546797600000,"participants":125730,"ranking50p":"62865","ranking25p":"62865","ranking10p":"31433","ranking5p":"6287","ranking1p":"1257","key1participants":91864,"key2participants":69406,"key3participants":51405,"key4participants":47585,"key5participants":44493,"key6participants":11832,"key7participants":11126,"key8participants":10517,"key9participants":6305},{"time":1546884000000,"participants":125730,"ranking50p":"62865","ranking25p":"62865","ranking10p":"31433","ranking5p":"6287","ranking1p":"1257","key1participants":91864,"key2participants":69406,"key3participants":51405,"key4participants":47585,"key5participants":44493,"key6participants":11832,"key7participants":11126,"key8participants":10517,"key9participants":6305},{"time":1546970400000,"participants":125730,"ranking50p":"62865","ranking25p":"62865","ranking10p":"31433","ranking5p":"6287","ranking1p":"1257","key1participants":91864,"key2participants":69406,"key3participants":51405,"key4participants":47585,"key5participants":44493,"key6participants":11832,"key7participants":11126,"key8participants":10517,"key9participants":6305},{"time":1547056800000,"participants":125730,"ranking50p":"62865","ranking25p":"62865","ranking10p":"31433","ranking5p":"6287","ranking1p":"1257","key1participants":91864,"key2participants":69406,"key3participants":51405,"key4participants":47585,"key5participants":44493,"key6participants":11832,"key7participants":11126,"key8participants":10517,"key9participants":6305},{"time":1547143200000,"participants":125730,"ranking50p":"62865","ranking25p":"62865","ranking10p":"31433","ranking5p":"6287","ranking1p":"1257","key1participants":91864,"key2participants":69406,"key3participants":51405,"key4participants":47585,"key5participants":44493,"key6participants":11832,"key7participants":11126,"key8participants":10517,"key9participants":6305},{"time":1547229600000,"participants":125730,"ranking50p":"62865","ranking25p":"62865","ranking10p":"31433","ranking5p":"6287","ranking1p":"1257","key1participants":91864,"key2participants":69406,"key3participants":51405,"key4participants":47585,"key5participants":44493,"key6participants":11832,"key7participants":11126,"key8participants":10517,"key9participants":6305},{"time":1547316000000,"participants":125730,"ranking50p":"62865","ranking25p":"62865","ranking10p":"31433","ranking5p":"6287","ranking1p":"1257","key1participants":91864,"key2participants":69406,"key3participants":51405,"key4participants":47585,"key5participants":44493,"key6participants":11832,"key7participants":11126,"key8participants":10517,"key9participants":6305},{"time":1547402400000,"participants":125730,"ranking50p":"62865","ranking25p":"62865","ranking10p":"31433","ranking5p":"6287","ranking1p":"1257","key1participants":91864,"key2participants":69406,"key3participants":51405,"key4participants":47585,"key5participants":44493,"key6participants":11832,"key7participants":11126,"key8participants":10517,"key9participants":6305},{"time":1547488800000,"participants":125730,"ranking50p":"62865","ranking25p":"62865","ranking10p":"31433","ranking5p":"6287","ranking1p":"1257","key1participants":91864,"key2participants":69406,"key3participants":51405,"key4participants":47585,"key5participants":44493,"key6participants":11832,"key7participants":11126,"key8participants":10517,"key9participants":6305},{"time":1547575200000,"participants":125730,"ranking50p":"62865","ranking25p":"62865","ranking10p":"31433","ranking5p":"6287","ranking1p":"1257","key1participants":91864,"key2participants":69406,"key3participants":51405,"key4participants":47585,"key5participants":44493,"key6participants":11832,"key7participants":11126,"key8participants":10517,"key9participants":6305},{"time":1547661600000,"participants":125730,"ranking50p":"62865","ranking25p":"62865","ranking10p":"31433","ranking5p":"6287","ranking1p":"1257","key1participants":91864,"key2participants":69406,"key3participants":51405,"key4participants":47585,"key5participants":44493,"key6participants":11832,"key7participants":11126,"key8participants":10517,"key9participants":6305},{"time":1547748000000,"participants":125730,"ranking50p":"62865","ranking25p":"62865","ranking10p":"31433","ranking5p":"6287","ranking1p":"1257","key1participants":91864,"key2participants":69406,"key3participants":51405,"key4participants":47585,"key5participants":44493,"key6participants":11832,"key7participants":11126,"key8participants":10517,"key9participants":6305},{"time":1547834400000,"participants":125730,"ranking50p":"62865","ranking25p":"62865","ranking10p":"31433","ranking5p":"6287","ranking1p":"1257","key1participants":91864,"key2participants":69406,"key3participants":51405,"key4participants":47585,"key5participants":44493,"key6participants":11832,"key7participants":11126,"key8participants":10517,"key9participants":6305},{"time":1547920800000,"participants":125730,"ranking50p":"62865","ranking25p":"62865","ranking10p":"31433","ranking5p":"6287","ranking1p":"1257","key1participants":91864,"key2participants":69406,"key3participants":51405,"key4participants":47585,"key5participants":44493,"key6participants":11832,"key7participants":11126,"key8participants":10517,"key9participants":6305},{"time":1548007200000,"participants":125730,"ranking50p":"62865","ranking25p":"62865","ranking10p":"31433","ranking5p":"6287","ranking1p":"1257","key1participants":91864,"key2participants":69406,"key3participants":51405,"key4participants":47585,"key5participants":44493,"key6participants":11832,"key7participants":11126,"key8participants":10517,"key9participants":6305},{"time":1548093600000,"participants":125730,"ranking50p":"62865","ranking25p":"62865","ranking10p":"31433","ranking5p":"6287","ranking1p":"1257","key1participants":91864,"key2participants":69406,"key3participants":51405,"key4participants":47585,"key5participants":44493,"key6participants":11832,"key7participants":11126,"key8participants":10517,"key9participants":6305},{"time":1548180000000,"participants":125730,"ranking50p":"62865","ranking25p":"62865","ranking10p":"31433","ranking5p":"6287","ranking1p":"1257","key1participants":91864,"key2participants":69406,"key3participants":51405,"key4participants":47585,"key5participants":44493,"key6participants":11832,"key7participants":11126,"key8participants":10517,"key9participants":6305},{"time":1548266400000,"participants":125730,"ranking50p":"62865","ranking25p":"62865","ranking10p":"31433","ranking5p":"6287","ranking1p":"1257","key1participants":91864,"key2participants":69406,"key3participants":51405,"key4participants":47585,"key5participants":44493,"key6participants":11832,"key7participants":11126,"key8participants":10517,"key9participants":6305}]}